{
  "version": "6.3.0",
  "flags": {},
  "shapes": [
    {
      "label": "Smoke",
      "points": [
        [
          4.204545454545507,
          32.727272727272734
        ],
        [
          91.70454545454551,
          39.54545454545456
        ],
        [
          181.47727272727278,
          196.36363636363637
        ],
        [
          232.6136363636364,
          200.90909090909093
        ],
        [
          281.4772727272728,
          127.04545454545455
        ],
        [
          404.2045454545455,
          115.6818181818182
        ],
        [
          446.25000000000006,
          202.04545454545456
        ],
        [
          656.4772727272727,
          219.09090909090912
        ],
        [
          693.9772727272727,
          279.31818181818187
        ],
        [
          779.2045454545455,
          262.2727272727273
        ],
        [
          1129.2045454545455,
          391.81818181818187
        ],
        [
          1170.1136363636365,
          479.3181818181818
        ],
        [
          951.9318181818182,
          478.1818181818182
        ],
        [
          864.4318181818182,
          460.0
        ],
        [
          804.2045454545455,
          422.5
        ],
        [
          639.4318181818182,
          419.0909090909091
        ],
        [
          396.25000000000006,
          361.1363636363637
        ],
        [
          332.61363636363643,
          338.40909090909093
        ],
        [
          151.93181818181822,
          345.22727272727275
        ],
        [
          5.340909090909142,
          261.1363636363637
        ]
      ],
      "group_id": null,
      "description": "",
      "shape_type": "polygon",
      "flags": {},
      "mask": null
    },
    {
      "label": "Smoke",
      "points": [
        [
          5.340909090909142,
          263.40909090909093
        ],
        [
          153.06818181818187,
          345.22727272727275
        ],
        [
          331.4772727272728,
          338.40909090909093
        ],
        [
          393.9772727272728,
          361.1363636363637
        ],
        [
          641.7045454545455,
          417.9545454545455
        ],
        [
          801.9318181818182,
          425.90909090909093
        ],
        [
          864.4318181818182,
          460.0
        ],
        [
          947.3863636363636,
          477.04545454545456
        ],
        [
          984.8863636363636,
          539.5454545454545
        ],
        [
          948.5227272727273,
          549.7727272727273
        ],
        [
          829.2045454545455,
          558.8636363636364
        ],
        [
          582.6136363636364,
          542.9545454545454
        ],
        [
          357.61363636363643,
          523.6363636363636
        ],
        [
          343.9772727272728,
          496.36363636363643
        ],
        [
          157.6136363636364,
          462.2727272727273
        ],
        [
          47.38636363636369,
          471.36363636363643
        ],
        [
          62.15909090909096,
          402.04545454545456
        ],
        [
          0.0,
          403.15543831168833
        ]
      ],
      "group_id": null,
      "description": "",
      "shape_type": "polygon",
      "flags": {},
      "mask": null
    }
  ],
  "imagePath": "Video6_110.jpg",
  "imageData": null,
  "imageHeight": 720,
  "imageWidth": 1280
}